purge_static/__init__.py
purge_static/__main__.py
purge_static/main.py
purge_static/utils.py
purge_static/cdn/__init__.py
purge_static/cdn/cloudflare.py
purge_static-0.2.0.dist-info/LICENSE
purge_static-0.2.0.dist-info/METADATA
purge_static-0.2.0.dist-info/WHEEL
purge_static-0.2.0.dist-info/entry_points.txt
purge_static-0.2.0.dist-info/top_level.txt
purge_static-0.2.0.dist-info/RECORD
